main/__init__.py
ayatotest2-0.0.0.2.dist-info/LICENSE.txt
ayatotest2-0.0.0.2.dist-info/METADATA
ayatotest2-0.0.0.2.dist-info/WHEEL
ayatotest2-0.0.0.2.dist-info/top_level.txt
ayatotest2-0.0.0.2.dist-info/RECORD
