Metadata-Version: 2.1
Name: ayatotest2
Version: 0.0.0.2
Author: realfelon
Keywords: python,discord,self,discordselfbot,discordself,sockets,automation
Classifier: Development Status :: 3 - Alpha
Classifier: Intended Audience :: Developers
Classifier: Programming Language :: Python :: 3
Classifier: Operating System :: Unix
Classifier: Operating System :: MacOS :: MacOS X
Classifier: Operating System :: Microsoft :: Windows
License-File: LICENSE.txt
Requires-Dist: requests
